<?xml version="1.0" encoding="UTF-8" ?>
<!DOCTYPE generatorConfiguration PUBLIC "-//mybatis.org//DTD MyBatis Generator Configuration 1.0//EN" "http://mybatis.org/dtd/mybatis-generator-config_1_0.dtd" >
<generatorConfiguration>
	<classPathEntry
		location="C:\Users\leerui\Desktop\mysql-connector-java-5.1.6.jar" />
	<context id="context1">
		<!-- 是否去除自动生成的注释 true：是 ： false:否 -->
		<commentGenerator>
			<property name="suppressAllComments" value="true" />
			<!--生成的注释包含时间戳 -->
			<property name="suppressDate" value="true" />
		</commentGenerator>
		<!-- 数据库配置 -->
		<jdbcConnection driverClass="com.mysql.jdbc.Driver"
			connectionURL="jdbc:mysql://120.78.85.230:3306/cloudSchool" userId="root"
			password="root" />
		<javaModelGenerator targetPackage="com.CloudSchool.domain"
			targetProject="CloudSchool/src/main/java" />
		<sqlMapGenerator targetPackage="mapper"
			targetProject="CloudSchool/src/main/resources" />
		<javaClientGenerator targetPackage="com.CloudSchool.dao"
			targetProject="CloudSchool/src/main/java" type="XMLMAPPER" />
		<!-- 表名称 -->

		
		
		<table schema="Zzy_class_committee" tableName="zzy_class_committee" enableCountByExample="false"
			enableUpdateByExample="false" enableDeleteByExample="false"
			enableSelectByExample="false" selectByExampleQueryId="false">
		</table>
		
		<table schema="Zzy_class_events" tableName="Zzy_class_events" enableCountByExample="false"
			enableUpdateByExample="false" enableDeleteByExample="false"
			enableSelectByExample="false" selectByExampleQueryId="false">
		</table>
		
		<table schema="Zzy_class_position" tableName="zzy_class_position" enableCountByExample="false"
			enableUpdateByExample="false" enableDeleteByExample="false"
			enableSelectByExample="false" selectByExampleQueryId="false">
		</table>
		
		<table schema="Zzy_class_schedule" tableName="zzy_class_schedule" enableCountByExample="false"
			enableUpdateByExample="false" enableDeleteByExample="false"
			enableSelectByExample="false" selectByExampleQueryId="false">
		</table>
		
		<table schema="Zzy_course" tableName="zzy_course" enableCountByExample="false"
			enableUpdateByExample="false" enableDeleteByExample="false"
			enableSelectByExample="false" selectByExampleQueryId="false">
		</table>
		
		<table schema="Zzy_course_events" tableName="zzy_course_events" enableCountByExample="false"
			enableUpdateByExample="false" enableDeleteByExample="false"
			enableSelectByExample="false" selectByExampleQueryId="false">
		</table>
		
		<table schema="Zzy_course_request" tableName="zzy_course_request" enableCountByExample="false"
			enableUpdateByExample="false" enableDeleteByExample="false"
			enableSelectByExample="false" selectByExampleQueryId="false">
		</table>
		
		<table schema="Zzy_event_type" tableName="Zzy_event_type" enableCountByExample="false"
			enableUpdateByExample="false" enableDeleteByExample="false"
			enableSelectByExample="false" selectByExampleQueryId="false">
		</table>
		
		<table schema="Zzy_grade" tableName="zzy_grade" enableCountByExample="false"
			enableUpdateByExample="false" enableDeleteByExample="false"
			enableSelectByExample="false" selectByExampleQueryId="false">
		</table>
		
		<table schema="Zzy_major" tableName="zzy_major" enableCountByExample="false"
			enableUpdateByExample="false" enableDeleteByExample="false"
			enableSelectByExample="false" selectByExampleQueryId="false">
		</table>
		
		<table schema="Zzy_realtime_classroom" tableName="zzy_realtime_classroom" enableCountByExample="false"
			enableUpdateByExample="false" enableDeleteByExample="false"
			enableSelectByExample="false" selectByExampleQueryId="false">
		</table>
		
		<table schema="Zzy_section" tableName="zzy_section" enableCountByExample="false"
			enableUpdateByExample="false" enableDeleteByExample="false"
			enableSelectByExample="false" selectByExampleQueryId="false">
		</table>
		
		<table schema="Zzy_teacher_ability" tableName="zzy_teacher_ability" enableCountByExample="false"
			enableUpdateByExample="false" enableDeleteByExample="false"
			enableSelectByExample="false" selectByExampleQueryId="false">
		</table>
		
		<table schema="Zzy_version" tableName="zzy_version" enableCountByExample="false"
			enableUpdateByExample="false" enableDeleteByExample="false"
			enableSelectByExample="false" selectByExampleQueryId="false">
		</table>
	</context>
</generatorConfiguration>